[
  {
    "name": "Thinking and Behaviour",
    "overThreshold": false,
    "riskOfHarm": true,
    "riskOfReoffending": true,
    "flaggedAsNeed": false
  },
  {
    "name": "Attitudes",
    "overThreshold": true,
    "riskOfHarm": false,
    "riskOfReoffending": true,
    "flaggedAsNeed": false
  },
  {
    "name": "4 - Education, Training and Employability",
    "overThreshold": false,
    "riskOfHarm": false,
    "riskOfReoffending": true,
    "flaggedAsNeed": false
  },
  {
    "name": "Emotional Well-Being",
    "overThreshold": false,
    "riskOfHarm": false,
    "riskOfReoffending": true,
    "flaggedAsNeed": true
  },
  {
    "name": "Health and Other Considerations",
    "overThreshold": false,
    "riskOfHarm": false,
    "riskOfReoffending": true,
    "flaggedAsNeed": false
  },
  {
    "name": "Accommodation",
    "overThreshold": false,
    "riskOfHarm": false,
    "riskOfReoffending": true,
    "flaggedAsNeed": false
  },
  {
    "name": "Education, Training and Employability",
    "overThreshold": false,
    "riskOfHarm": false,
    "riskOfReoffending": true,
    "flaggedAsNeed": false
  },
  {
    "name": "Financial Management and Income",
    "overThreshold": false,
    "riskOfHarm": false,
    "riskOfReoffending": true,
    "flaggedAsNeed": false
  },
  {
    "name": "Relationships",
    "overThreshold": true,
    "riskOfHarm": true,
    "riskOfReoffending": true,
    "flaggedAsNeed": true
  },
  {
    "name": "Lifestyle and Associates",
    "overThreshold": true,
    "riskOfHarm": false,
    "riskOfReoffending": false,
    "flaggedAsNeed": false
  },
  {
    "name": "Drug Misuse",
    "overThreshold": false,
    "riskOfHarm": false,
    "riskOfReoffending": false,
    "flaggedAsNeed": true
  },
  {
    "name": "Alcohol Misuse",
    "overThreshold": false,
    "riskOfHarm": true,
    "riskOfReoffending": true,
    "flaggedAsNeed": false
  }
]
